CV_Robot/__init__.py
CV_Robot/opencv_api.py
CV_Robot/robot.py
CV_Robot/vision.py
CV_Robot/Models/Yolo v3/yolov3.cfg
CV_Robot/Models/Yolo v3/yolov3.names
cv_robot-0.4.6.dist-info/licenses/LICENSE
cv_robot-0.4.6.dist-info/METADATA
cv_robot-0.4.6.dist-info/WHEEL
cv_robot-0.4.6.dist-info/top_level.txt
cv_robot-0.4.6.dist-info/RECORD
