Metadata-Version: 2.4
Name: CV_Robot
Version: 0.4.6
Summary: Computer vision robotics project
Home-page: https://github.com/RobertJN64/CV_Robot
Author: Robert Nies
Author-email: robertjnies@gmail.com
License: MIT
Classifier: Programming Language :: Python
Classifier: Programming Language :: Python :: 3
Classifier: Programming Language :: Python :: 3 :: Only
Classifier: Programming Language :: Python :: 3.10
Classifier: Programming Language :: Python :: 3.11
Classifier: Programming Language :: Python :: 3.12
Classifier: Programming Language :: Python :: 3.13
Classifier: Programming Language :: Python :: 3.14
Requires-Python: >=3.10
License-File: LICENSE
Requires-Dist: requests
Requires-Dist: matplotlib
Requires-Dist: wget
Requires-Dist: opencv-python==4.5.5.64
Dynamic: license-file
